<persistence xmlns:xsi="http://www.w3.org/2001/XMLSchema-instance"
	xsi:schemaLocation="http://java.sun.com/xml/ns/persistence http://java.sun.com/xml/ns/persistence/persistence_2_0.xsd"
	version="2.0" xmlns="http://java.sun.com/xml/ns/persistence">
	<persistence-unit name="antt" transaction-type="RESOURCE_LOCAL">
		<provider>org.eclipse.persistence.jpa.PersistenceProvider</provider>
		<class>org.tephrochronology.model.Volcano</class>
		<class>org.tephrochronology.model.Country</class>
		<class>org.tephrochronology.model.RockType</class>
		<class>org.tephrochronology.model.VolcanoType</class>
		<class>org.tephrochronology.model.Region</class>
		<class>org.tephrochronology.model.Subregion</class>
		<class>org.tephrochronology.model.TectonicType</class>
		<class>org.tephrochronology.model.SiteType</class>
		<class>org.tephrochronology.model.Site</class>
		<class>org.tephrochronology.model.Instrument</class>
		<class>org.tephrochronology.model.Ref</class>
		<class>org.tephrochronology.model.Sample</class>
		<class>org.tephrochronology.model.GrainSize</class>
		<class>org.tephrochronology.model.Image</class>
		<class>org.tephrochronology.model.IceCoreSample</class>
		<class>org.tephrochronology.model.BIASample</class>
		<class>org.tephrochronology.model.CoreType</class>
		<class>org.tephrochronology.model.AquaticSample</class>
		<class>org.tephrochronology.model.LakeSample</class>
		<class>org.tephrochronology.model.MarineSample</class>
		<class>org.tephrochronology.model.OutcropSample</class>
		<class>org.tephrochronology.model.MethodType</class>
		<class>org.tephrochronology.model.LocalDateAttributeConverter</class>
	</persistence-unit>
</persistence>